codehackscalculator/__init__.py
codehackspackage-0.2.0.dist-info/licenses/LICENCE.txt
codehackspackage-0.2.0.dist-info/METADATA
codehackspackage-0.2.0.dist-info/WHEEL
codehackspackage-0.2.0.dist-info/top_level.txt
codehackspackage-0.2.0.dist-info/RECORD
