Metadata-Version: 2.4
Name: codehackspackage
Version: 0.2.0
Summary: Add your description here
Home-page: https://bogoljubstankovic.com
Author: Bogoljub Stankovic
Author-email: bob.stankovic@gov.ab.ca
Requires-Python: >=3.6
License-File: LICENCE.txt
Requires-Dist: setuptools>=80.9.0
Requires-Dist: tqdm>=4.67.1
Requires-Dist: twine>=6.2.0
Requires-Dist: wheel>=0.45.1
Dynamic: author
Dynamic: author-email
Dynamic: home-page
Dynamic: license-file
Dynamic: requires-python
